gridded_obs/__init__.py
gridded_obs/aggregate.py
gridded_obs/common.py
gridded_obs/dct.py
gridded_obs/lmin_from_fss.py
gridded_obs/verify.py
gridded_obs/plot/__init__.py
gridded_obs/plot/common.py
gridded_obs/plot/compare_fields.py
gridded_obs/plot/time_series.py
gridded_obs/plot/twod_panels.py
gridded_obs/readers/__init__.py
gridded_obs/readers/instaccum.py
gridded_obs/readers/modelfst.py
gridded_obs/readers/reader_init.py
gridded_obs/sql/__init__.py
gridded_obs/sql/handler.py
gridded_obs-1.0.5.dist-info/licenses/LICENSE
scripts/batch_submit_gridded_obs.sh
scripts/batch_wrapper_gridded_obs.sh
scripts/launch_aggregate.sh
scripts/launch_verification.sh
scripts/set_env.sh
scripts/verif_N2FC80E19V1_30m.sh
gridded_obs-1.0.5.dist-info/METADATA
gridded_obs-1.0.5.dist-info/WHEEL
gridded_obs-1.0.5.dist-info/top_level.txt
gridded_obs-1.0.5.dist-info/RECORD
