Metadata-Version: 2.4
Name: gridded_obs
Version: 1.0.5
Summary: Efficient verification of gridded observations
Author-email: Dominik Jacques <dominik.jacques@gmail.com>
License: GPL-3.0-or-later
Project-URL: Homepage, https://gitlab.science.gc.ca/dja001/gridded_obs_py
Project-URL: Repository, https://gitlab.science.gc.ca/dja001/gridded_obs_py.git
Requires-Python: >=3.7
License-File: LICENSE
Requires-Dist: numpy>=1.20
Requires-Dist: scipy
Requires-Dist: cartopy
Requires-Dist: matplotlib
Requires-Dist: dask[complete]
Provides-Extra: test
Requires-Dist: pytest; extra == "test"
Requires-Dist: domcmc; extra == "test"
Provides-Extra: build
Requires-Dist: packaging; extra == "build"
Requires-Dist: twine; extra == "build"
Dynamic: license-file
